maze/__init__.py
maze/__main__.py
maze/__version__.py
maze/bio.py
maze/chem.py
maze/network.py
maze/smiles.py
maze/utils.py
maze/resource/opsin-cli-2.8.0-jar-with-dependencies.jar
mazeai-0.0.8.dist-info/LICENSE
mazeai-0.0.8.dist-info/METADATA
mazeai-0.0.8.dist-info/WHEEL
mazeai-0.0.8.dist-info/entry_points.txt
mazeai-0.0.8.dist-info/top_level.txt
mazeai-0.0.8.dist-info/RECORD
