Metadata-Version: 2.1
Name: mazeai
Version: 0.0.8
Summary: A General Tool Set for Science Researches
Home-page: https://github.com/zhaisilong/mazeai
Author: Zhai Silong
Author-email: zhaisilong@outlook.com
License: MIT
Classifier: Development Status :: 2 - Pre-Alpha
Classifier: License :: OSI Approved :: MIT License
Classifier: Programming Language :: Python :: 3.7
Requires-Python: >=3.6
License-File: LICENSE
Requires-Dist: rich
Requires-Dist: ipykernel
Requires-Dist: tqdm
Requires-Dist: loguru
Requires-Dist: hydra-core
Provides-Extra: chem
Requires-Dist: jpype1 ; extra == 'chem'
Requires-Dist: molvs ; extra == 'chem'
